{
    "Aid": "01",
    "Place": "दिल्ली",
    "Drama": "गार्बो (हिन्दी)",
    "Writer": "महेश एलकुंचवार",
    "Translation": "सुधीर कुलकर्णी",
    "Director": "बिपिन कुमार",
    "Asst-director": "शिल्पा शुक्ला",
    "Music": "शिल्पा शुक्ला",
    "Light": "हिमांशु बी. जोशी",
    "Article": "भारती शर्मा",
    "Artist": "मोहित त्रिपाठी (बुद्दिजीवी), संजय गौतम (श्रीमंत), भारती शर्मा (गार्बो) व गौरव कौशिक (पन्सी)",
    "Venue": "श्रीराम सेण्टर, सभागार",
    "ForeignKeyId": "074.226",
    "ForeignKeyType": "EventID"
}