{
    "Aid": "01",
    "Drama": "आफताब फैजाबादी (उर्दू)",
    "Writer": "एडमंड शैस्टैंड (फ्रेंच)",
    "Translation": "एगिल किप्सटे",
    "Translator": "जे. एन. कौशल एवं सहयोगी",
    "Director": "इजिल किप्टसे",
    "Music": "लोकेन्द्र त्रिवेदी",
    "Voice": "लोकेन्द्र त्रिवेदी",
    "Musicassistant": "ओम प्रकाश, राकेश प्रसन्ना व अन्य",
    "Costume": "अनिला सिंह",
    "Costumeassistant": "उषा बैनर्जी, नूतन सूर्या व अन्य",
    "Make-up": "ललित मोहन व अन्य",
    "Stage": "निसार अल्लाना",
    "Stagecontent": "निसार अल्लाना",
    "Light": "जी. एस. मराठे",
    "Lightingdesignasst": "सुरेखा सीकरी व अन्य",
    "Artist": "प्रमोद मुत्थु (आफताब फैज़ाबादी), डौली आहलुवालिया (रुक्साना), हेमा सहाय (आया), अनंग देसाई (गुलाम अब्बास चंगेज़ी), लोकेन्द्र त्रिवेदी (सुल्तान अहमद) व अन्य",
    "ForeignKeyId": "075.021",
    "ForeignKeyType": "EventID",
    "EventID": "075.021"
}