{
    "Aid": "01",
    "Place": "दिल्ली",
    "Drama": "सीमापार (हिन्दी)",
    "Writer": "प्रसन्ना (कन्नड)",
    "Director": "प्रसन्ना (कन्नड)",
    "Translation": "सिद्धलिंगपट्टणशेट्टी",
    "Asst-director": "साउती चक्रवर्ती",
    "Music": "काजल घोष",
    "Dress": "डौली आहलुवालिया तिवारी",
    "Stage": "जैक ओ याह",
    "Light": "सुरेश भारद्वाज",
    "Photographer": "एस. त्यागराजन",
    "Artist": "टीकम जोशी, आसिफ अली (भारतेन्दु), सुरेश शर्मा, गोविन्द पाण्डे (मृत्यु), दक्षिण शर्मा/नसरीन इसहाक (मल्लिका), व अन्य",
    "Venue": "अभिमंच सभागार, दिल्ली",
    "ForeignKeyId": "075.230",
    "ForeignKeyType": "EventID",
    "EventID": "075.230"
}