{
    "id": "001/057.10/04813",
    "AccessionCards": "054.053, 054.054, 056.144, 056.145, 056.477, 056.478, 064.225, 064.226, 066.384, 066.385, 067.257, 067.258, 067.770, 067.771",
    "Date": "06-09-2006",
    "AccessionNumber": "4813",
    "Type": "Brochure",
    "States": "असम, केरल, जम्मू और कश्मीर, दिल्ली, महाराष्ट्र, पश्चिम बंगाल, बिहार",
    "Places": "Guwahati, Thiruvananthapuram, Jammu, Delhi, Mumbai, Kolkata, Patna",
    "AccessLevel": 0,
    "Troupe": "सीगल",
    "Title": "जात्रा (असमी)",
    "Story": "इमरान हूसैन",
    "Article": "बहरूल इस्लाम",
    "Direction": "बहरूल इस्लाम",
    "Music": "बहरूल इस्लाम",
    "Projection": "बहरूल इस्लाम",
    "Lightconcept": "अकन दास, सैइलन ककारी",
    "Stage": "ध्रुव एवं मून रहमान",
    "Costume": "निर्मली बुरागोहेन मोरोमी",
    "Material": "निर्मली बुरागोहेन मोरोमी",
    "Artist": "बहरूल इस्लाम, भागीरथी व अन्य",
    "Size": "24X15.5 से. मी.",
    "Pages": "24",
    "Venue": "आर. आर. एल. अॉडीटोरियम, भुवनेश्वर",
    "Desc": "सहयोग - ओड़िसा संगीत नाटक अकेडमी, भुवनेश्वर एवं नाटक, ग्रुप, निर्देशक व निर्देशकीय जानकारी, साथ में रंग संगम थियेटर फेस्टिवल में प्रस्तुत नाटक ।"
}
