{
    "id": "001/058.05/01823",
    "AccessionCards": "054.110, 054.111, 054.112, 056.024, 056.576, 064.328, 064.329, 067.506, 069.406, 069.407, 069.417",
    "Date": "08-10-1990",
    "AccessionNumber": "1823",
    "Type": "Brochure",
    "States": "आंध्र प्रदेश, कर्नाटक, तमिल नाडु, दिल्ली, पॉण्डिचेरी,",
    "Places": "Vijayawada, Bangalore, Gandhigram, Delhi",
    "AccessLevel": 0,
    "Troupe": "नवोदय आर्ट्स अकादमी, थियेटर रिसर्च आर्टिस्ट्स सेंटर & रंगविभंग",
    "Title": "मरीचिका (तेलुगु नाटक), अग्नि (मलयालम नाटक) & मालविकाग्नि (कन्नड़ नाटक)",
    "Direction": "जी. उदय भानु, के. मणि कांत दास & बी. आर. वी. यैथल",
    "Event": "नाट्य समारोह, 08-14 अक्टूबर 1990",
    "Host": "संगीत नाटक अकादमी, दिल्ली साउथ जॉन कल्चरल सेंटर, थाँज़ावुर एवं म्युनिसिपल कारपोरेशॅन, विजयवाड़ा",
    "Size": "21X14 से. मी.",
    "Pages": "6",
    "Venue": "श्री तुम्मलापल्ली वारी क्षेत्रीय कला क्षेत्रम्, विजयवाड़ा",
    "Writer": "व्याल एन. वसुदेवन पिल्लई & कालिदास",
    "Version": "के. वी. शुब्बन्ना"
}