{
    "id": "001/006.06/04563",
    "AccessionCards": "054.413, 054.414",
    "State": "उत्तर प्रदेश",
    "Place": "कानपुर",
    "Date": "12-03-2001",
    "AccessionNumber": "4563",
    "Type": "Brochure",
    "AccessLevel": 0,
    "Troupe": "दर्पण",
    "Title": "द जनपथ Kiss",
    "Writer": "अखिलेश्वर झा",
    "Dramatization": "रंजीत कपूर",
    "Projection": "रंजीत कपूर",
    "Direction": "रंजीत कपूर",
    "Codirection": "लक्ष्मीकांत `सनी' राकेश वर्मा",
    "Costume": "निष्ठा शर्मा, मेघना वर्मा, अक्षय श्रीवास्तव",
    "Stage": "राजीव गोयल, रहमान शह एवं अन्य",
    "Event": "सम्भागीय नाट्य समारोह, 25 मार्च 2001",
    "Size": "21X9.5 से. मी.",
    "Pages": "5",
    "Venue": "लाजपत भवन, मोतीझील, कानपुर",
    "Desc": "अखिलेश्वर झा के उपन्यास पर आधारित दूसरी प्रस्तुति-25 मार्च 2001, सम्भागीय नाट्य समारोह, मनकापुर ।"
}